commands/__init__.py
commands/manga_archive.py
commands/manga_ascii.py
commands/manga_extract.py
commands/manga_search.py
mangatools-0.2.0.dist-info/LICENSE
mangatools-0.2.0.dist-info/METADATA
mangatools-0.2.0.dist-info/WHEEL
mangatools-0.2.0.dist-info/entry_points.txt
mangatools-0.2.0.dist-info/top_level.txt
mangatools-0.2.0.dist-info/RECORD
