Metadata-Version: 2.1
Name: mangatools
Version: 0.2.0
Summary: tools for manga
Home-page: https://github.com/Arrow420/mangatools
Author: Arrow
Author-email: arrowsoftwaresolutions@gmail.com
License: MIT
Keywords: manga,tools,python
Platform: UNKNOWN
Classifier: Programming Language :: Python :: 3
Classifier: License :: OSI Approved :: MIT License
Classifier: Operating System :: OS Independent
Requires-Python: >=3.6
License-File: LICENSE
Requires-Dist: click
Requires-Dist: requests
Requires-Dist: wheel
Requires-Dist: natsort
